MultiChoice.py
MultiChoice-0.3.5.dist-info/METADATA
MultiChoice-0.3.5.dist-info/WHEEL
MultiChoice-0.3.5.dist-info/top_level.txt
MultiChoice-0.3.5.dist-info/RECORD
