Metadata-Version: 2.1
Name: MultiChoice
Version: 0.3.5
Summary: Framework for generating formatted user input questions.
Home-page: UNKNOWN
Author: Robert Sharp
Author-email: webmaster@sharpdesigndigital.com
License: Free for non-commercial use
Keywords: Questionnaire,Multiple Choice,Quiz Framework,Terminal Survey
Platform: UNKNOWN
Classifier: Development Status :: 3 - Alpha
Classifier: Programming Language :: Python :: 3.6
Requires-Python: >=3.6
